crimson/code_extractor/__init__.py
crimson/code_extractor/extract.py
crimson/code_extractor/specs.py
crimson/code_extractor/beta/__init__.py
crimson/code_extractor/beta/_get_func_info.py
crimson/code_extractor/beta/func_info.py
crimson_code_extractor-0.1.6.dist-info/LICENSE
crimson_code_extractor-0.1.6.dist-info/METADATA
crimson_code_extractor-0.1.6.dist-info/WHEEL
crimson_code_extractor-0.1.6.dist-info/top_level.txt
crimson_code_extractor-0.1.6.dist-info/RECORD
